search_x_likes/__init__.py
search_x_likes/bm25_search.py
search_x_likes/convert_archive.py
search_x_likes/cosine_search.py
search_x_likes/embed_posts.py
search_x_likes/exact_search.py
search_x_likes/list_likes_in_archive.py
search_x_likes-0.0.4.dist-info/LICENSE
search_x_likes-0.0.4.dist-info/METADATA
search_x_likes-0.0.4.dist-info/WHEEL
search_x_likes-0.0.4.dist-info/top_level.txt
search_x_likes-0.0.4.dist-info/RECORD
