Metadata-Version: 2.2
Name: search-x-likes
Version: 0.0.4
Summary: Search posts from x that you have liked yourself usign the archive download files
Author-email: Lode Nachtergaele <cast42@gmail.com>
Project-URL: Homepage, https://cast42.github.io/search-x-likes/
Project-URL: Repository, https://github.com/cast42/search-x-likes
Project-URL: Documentation, https://cast42.github.io/search-x-likes/
Keywords: python
Requires-Python: <4.0,>=3.9
License-File: LICENSE
Requires-Dist: bm25s>=0.2.1
Requires-Dist: openai>=1.48.0
Requires-Dist: pandas-stubs>=2.2.2.240807
Requires-Dist: pandas>=2.2.3
Requires-Dist: pystemmer>=2.2.0.1
Requires-Dist: textual>=0.81.0
Requires-Dist: fastparquet>=2024.11.0
Requires-Dist: scikit-learn>=1.6.0
